ibl_pipeline/__init__.py
ibl_pipeline/analyses/__init__.py
ibl_pipeline/utils/__init__.py
ibl_pipeline/utils/psychofit.py
ibl_pipeline_light-0.1.2.dist-info/METADATA
ibl_pipeline_light-0.1.2.dist-info/WHEEL
ibl_pipeline_light-0.1.2.dist-info/top_level.txt
ibl_pipeline_light-0.1.2.dist-info/RECORD
